MANIFEST.in
README.rst
requirements.txt
setup.py
test/test_connection.py
tornado_psycopg2/__init__.py
tornado_psycopg2/connection.py
tornado_psycopg2/cursor.py
tornado_psycopg2.egg-info/PKG-INFO
tornado_psycopg2.egg-info/SOURCES.txt
tornado_psycopg2.egg-info/dependency_links.txt
tornado_psycopg2.egg-info/requires.txt
tornado_psycopg2.egg-info/top_level.txt