Metadata-Version: 1.1
Name: tornado-psycopg2
Version: 0.2
Summary: Tornado driver for support asynchronous mode for psycopg2.
Home-page: UNKNOWN
Author: Dmitry Orlov
Author-email: me@mosquito.su
License: MIT
Platform: all
Classifier: Environment :: Console
Classifier: Programming Language :: Python
Requires: Python (>2.6)
